i2ftps/__init__.py
i2ftps/client.py
i2ftps/config.py
i2ftps/process_manage.py
i2ftps/server.py
i2ftps-0.3.9.dist-info/METADATA
i2ftps-0.3.9.dist-info/WHEEL
i2ftps-0.3.9.dist-info/entry_points.txt
i2ftps-0.3.9.dist-info/top_level.txt
i2ftps-0.3.9.dist-info/RECORD
