Metadata-Version: 2.1
Name: i2ftps
Version: 0.3.9
Summary: A FTP server based on I2TCP
Home-page: https://github.com/i2cy/i2ftp-server
Author: I2cy Cloud
Author-email: i2cy@outlook.com
License: UNKNOWN
Project-URL: Bug Tracker, https://github.com/i2cy/I2FTPServer/issues
Project-URL: Source Code, https://github.com/i2cy/I2FTPServer
Platform: UNKNOWN
Classifier: Programming Language :: Python :: 3
Classifier: License :: OSI Approved :: MIT License
Classifier: Operating System :: OS Independent
Requires-Python: >=3.6
Requires-Dist: i2cylib (>=1.8.14)
